{
  "moduleId": "polytoria.character.animation",
  "kind": "Action",
  "apiGroup": "Runtime Gameplay",
  "apiSurface": "Gameplay",
  "runtimeFamily": "Server",
  "category": "Actions",
  "subcategory": "Characters",
  "idBase": "ACT_PlayCharacterOneShotAnimation",
  "type": "PlayCharacterOneShotAnimation",
  "apiType": "Animator.PlayOneShotAnimation",
  "apiReferences": [
    { "type": "CharacterModel", "memberKind": "Property", "member": "Animator", "coverage": "Direct" },
    { "type": "Animator", "memberKind": "Method", "member": "PlayOneShotAnimation", "coverage": "Direct" }
  ],
  "label": "Play Character One Shot",
  "value": "target=Self;animation=Wave",
  "description": "Plays a one-shot character animation without replacing the main loop.",
  "status": "Ready",
  "previewTemplate": "Play one-shot ${animation} on ${target}",
  "searchKeywords": ["character", "animation", "animator", "one shot", "emote", "wave", "attack"],
  "corePack": true,
  "familyFolder": "Polytoria Characters",
  "utilityLayer": "Gameplay",
  "parameters": [
    { "key": "target", "label": "Character", "type": "Object Path", "control": "SceneObject", "required": true, "default": "Self", "description": "Character to animate.", "valueSource": "Target Context", "acceptedObjectGroups": ["CharacterModelObject"] },
    { "key": "animation", "label": "Animation", "type": "String", "control": "Text", "required": true, "default": "Wave", "description": "One-shot animation key to play.", "valueSource": "Suggested Value" }
  ],
  "beginnerSummary": "Do play a short character animation once.",
  "surface": "UserFacing",
  "palettePath": ["Players", "Character Animation"]
}
